print_tree/__init__.py
print_tree/compat.py
print_tree/print_tree.py
tests/__init__.py
tests/test_helper.py
tests/test_maxrecursion.py
tests/test_output.py
tests/test_terminal_width.py
tests/utils.py
print_tree2-0.9.10.dist-info/LICENSE
print_tree2-0.9.10.dist-info/METADATA
print_tree2-0.9.10.dist-info/WHEEL
print_tree2-0.9.10.dist-info/top_level.txt
print_tree2-0.9.10.dist-info/RECORD
