Metadata-Version: 2.1
Name: print-tree2
Version: 0.9.10
Summary: Print trees
Home-page: https://github.com/liwt31/print-tree
Author: Weitang Li
Author-email: liwt31@163.com
License: MIT
Platform: UNKNOWN
Requires-Dist: ipython
